{"source/main.ptx": ["frontmatter", "course-syllabus", "basics-of-functions", "bf1", "bf2", "bf3", "bf4", "graphs-of-functions", "gr1", "gr2", "gr3", "gr4", "gr5", "exponential-and-logarithmic-functions", "el1", "el2", "el3", "trigonometric-functions", "tf1", "tf2", "tf3", "tf4"], "source/syllabus/syllabus.ptx": ["syllabus"], "source/syllabus/components.ptx": ["components"], "source/syllabus/rubrics.ptx": ["rubrics"], "source/syllabus/policies.ptx": ["policies"], "source/syllabus/support.ptx": ["support"]}